github2pypi/__init__.py
github2pypi/generate_pypi_readme.py
github2pypi/publish_to_pypi.py
github2pypi/replace_url.py
github2pypi/run_tests.py
pyoctomap/__init__.py
pyoctomap/color_octree.cpp
pyoctomap/color_octree.cpython-312-x86_64-linux-gnu.so
pyoctomap/color_octree.pyx
pyoctomap/counting_octree.cpp
pyoctomap/counting_octree.cpython-312-x86_64-linux-gnu.so
pyoctomap/counting_octree.pyx
pyoctomap/dynamicEDT3D_defs.pxd
pyoctomap/include_and_setting.h
pyoctomap/octomap.cpp
pyoctomap/octomap.cpython-312-x86_64-linux-gnu.so
pyoctomap/octomap.pyx
pyoctomap/octomap_defs.pxd
pyoctomap/octomap_math.pxd
pyoctomap/octomap_std.pxd
pyoctomap/octomap_trees.pxd
pyoctomap/octree.cpp
pyoctomap/octree.cpython-312-x86_64-linux-gnu.so
pyoctomap/octree.pxd
pyoctomap/octree.pyx
pyoctomap/octree_base.cpp
pyoctomap/octree_base.cpython-312-x86_64-linux-gnu.so
pyoctomap/octree_base.pxd
pyoctomap/octree_base.pyx
pyoctomap/octree_iterators.cpp
pyoctomap/octree_iterators.cpython-312-x86_64-linux-gnu.so
pyoctomap/octree_iterators.pyx
pyoctomap/pointcloud.cpp
pyoctomap/pointcloud.cpython-312-x86_64-linux-gnu.so
pyoctomap/pointcloud.pyx
pyoctomap/stamped_octree.cpp
pyoctomap/stamped_octree.cpython-312-x86_64-linux-gnu.so
pyoctomap/stamped_octree.pyx
pyoctomap/lib/libdynamicedt3d.a
pyoctomap/lib/libdynamicedt3d.so
pyoctomap/lib/libdynamicedt3d.so.1.10
pyoctomap/lib/libdynamicedt3d.so.1.10.0
pyoctomap/lib/libltdl.a
pyoctomap/lib/libltdl.so
pyoctomap/lib/libltdl.so.7
pyoctomap/lib/libltdl.so.7.3.3
pyoctomap/lib/liboctomap.a
pyoctomap/lib/liboctomap.so
pyoctomap/lib/liboctomap.so.1.10
pyoctomap/lib/liboctomap.so.1.10.0
pyoctomap/lib/liboctomath.a
pyoctomap/lib/liboctomath.so
pyoctomap/lib/liboctomath.so.1.10
pyoctomap/lib/liboctomath.so.1.10.0
pyoctomap.libs/liboctomap-3c05658b.so.1.10
pyoctomap.libs/liboctomath-aee0898c.so.1.10.0
pyoctomap-1.1.2.dist-info/METADATA
pyoctomap-1.1.2.dist-info/WHEEL
pyoctomap-1.1.2.dist-info/entry_points.txt
pyoctomap-1.1.2.dist-info/top_level.txt
pyoctomap-1.1.2.dist-info/RECORD
pyoctomap-1.1.2.dist-info/licenses/LICENSE
