Metadata-Version: 2.1
Name: pyoctomap
Version: 1.1.2
Summary: Python binding of the OctoMap library with bundled shared libraries.
Author-email: Spinkoo <lespinkoo@gmail.com>
License: MIT License
Project-URL: Homepage, https://spinkoo.github.io/pyoctomap/
Project-URL: Repository, https://github.com/Spinkoo/pyoctomap
Project-URL: Documentation, https://github.com/Spinkoo/pyoctomap/tree/main/docs
Project-URL: Bug Tracker, https://github.com/Spinkoo/pyoctomap/issues
Keywords: octomap,occupancy,mapping,robotics,3d
Classifier: Development Status :: 5 - Production/Stable
Classifier: Intended Audience :: Developers
Classifier: Intended Audience :: Science/Research
Classifier: Natural Language :: English
Classifier: Programming Language :: Python :: 3 :: Only
Classifier: Topic :: Scientific/Engineering
Classifier: Topic :: Software Development :: Libraries :: Python Modules
Requires-Python: >=3.8
License-File: LICENSE
Requires-Dist: numpy>=1.16.0
Provides-Extra: dev
Requires-Dist: pytest>=6.0; extra == "dev"
Requires-Dist: pytest-cov; extra == "dev"
Requires-Dist: black; extra == "dev"
Requires-Dist: flake8; extra == "dev"
Requires-Dist: mypy; extra == "dev"
Requires-Dist: twine; extra == "dev"
Requires-Dist: build; extra == "dev"
Provides-Extra: visualization
Requires-Dist: matplotlib>=3.0.0; extra == "visualization"
Requires-Dist: open3d>=0.13.0; extra == "visualization"
